{
    "sentences": [
        {
            "project_id": "13",
            "sentence": "परिचय।",
            "sentence_id": "oct-31-2022-part1Patient_Information_Sheet-Riya_Lal_Study_hin_target_003INFOSHEET"
        },
        {
            "project_id": "13",
            "sentence": "आपको एक शोध अध्ययन में भाग लेने के लिए चुना गया है।",
            "sentence_id": "oct-31-2022-part1Patient_Information_Sheet-Riya_Lal_Study_hin_target_004"
        },
        {
            "project_id": "13",
            "sentence": "इससे पहले कि आप तय यह करें।",
            "sentence_id": "oct-31-2022-part1Patient_Information_Sheet-Riya_Lal_Study_hin_target_005a"
        },
        {
            "project_id": "13",
            "sentence": "कि क्या आप इसमें भाग लेना चाहते हैं.",
            "sentence_id": "oct-31-2022-part1Patient_Information_Sheet-Riya_Lal_Study_hin_target_005b"
        },
        {
            "project_id": "13",
            "sentence": "कृपया अपने जोखिमों और लाभों के बारे में जानने के लिये नीचे दिए गए अध्ययन के बारे में पढें।",
            "sentence_id": "oct-31-2022-part1Patient_Information_Sheet-Riya_Lal_Study_hin_target_005c"
        },
        {
            "project_id": "13",
            "sentence": "हम यह सुनिश्चित करेंगे।",
            "sentence_id": "oct-31-2022-part1Patient_Information_Sheet-Riya_Lal_Study_hin_target_007a"
        },
        {
            "project_id": "13",
            "sentence": "कि आपके सभी सवालों के जवाब दिए जाएं।",
            "sentence_id": "oct-31-2022-part1Patient_Information_Sheet-Riya_Lal_Study_hin_target_007b"
        },
        {
            "project_id": "13",
            "sentence": "इस अध्ययन में भागीदारी स्वैच्छिक है।",
            "sentence_id": "oct-31-2022-part1Patient_Information_Sheet-Riya_Lal_Study_hin_target_008"
        },
        {
            "project_id": "13",
            "sentence": "पृष्ठभूमि।",
            "sentence_id": "oct-31-2022-part1Patient_Information_Sheet-Riya_Lal_Study_hin_target_009H"
        },
        {
            "project_id": "13",
            "sentence": "हम एक शोध अध्ययन में भाग लेने के लिए आपसे संपर्क कर रहे हैं ।",
            "sentence_id": "oct-31-2022-part1Patient_Information_Sheet-Riya_Lal_Study_hin_target_010a"
        },
        {
            "project_id": "13",
            "sentence": "क्योंकि आप नाक के माध्यम से मस्तिष्क ट्यूमर के लिए शल्य-चिकित्सा करवा रहे हैं।",
            "sentence_id": "oct-31-2022-part1Patient_Information_Sheet-Riya_Lal_Study_hin_target_010b"
        },
        {
            "project_id": "13",
            "sentence": "शल्य-चिकित्सा से पहले आपको एनेस्थेसियोलॉजिस्ट द्वारा (सामान्य एनेस्थीसिया) देकर सुला दिया जाएगा।",
            "sentence_id": "oct-31-2022-part1Patient_Information_Sheet-Riya_Lal_Study_hin_target_011"
        },
        {
            "project_id": "13",
            "sentence": "आपको जितना समय चाहिए उतना समय लें ।",
            "sentence_id": "oct-31-2022-part1Patient_Information_Sheet-Riya_Lal_Study_hin_target_006a"
        },
        {
            "project_id": "13",
            "sentence": "कि क्या आपको अध्ययन के बारे में कोई संदेह है।",
            "sentence_id": "oct-31-2022-part1Patient_Information_Sheet-Riya_Lal_Study_hin_target_006c"
        },
        {
            "project_id": "13",
            "sentence": "और अध्ययन जांचकर्ताओं से यह पूछने के लिए स्वतंत्र महसूस करें।",
            "sentence_id": "oct-31-2022-part1Patient_Information_Sheet-Riya_Lal_Study_hin_target_006b"
        },
        {
            "project_id": "13",
            "sentence": "शल्य-चिकित्सा के दौरान एनेस्थेसियोलॉजिस्ट आपके सभी महत्वपूर्ण एवं शल्य-चिकित्सा के समय आवश्यक मापदंडों, जैसे कि श्वास, दर्द, नींद की स्थिति, रक्तचाप, हृदय गति नियंत्रण का ध्यान रखेगा।",
            "sentence_id": "oct-31-2022-part1Patient_Information_Sheet-Riya_Lal_Study_hin_target_012"
        },
        {
            "project_id": "13",
            "sentence": "जैसे ही शल्य-चिकित्सक आपकी नाक और खोपडी की हड्डी के आधार के माध्यम से ट्यूमर के पास पहुंचता है, हम नाक के माध्यम से मस्तिष्क की परतों को कवर करने के उभार को नियंत्रित करने के लिए कुछ उपाय (आपकी श्वास दर को नियंत्रित करके) करते हैं।",
            "sentence_id": "oct-31-2022-part1Patient_Information_Sheet-Riya_Lal_Study_hin_target_013"
        },
        {
            "project_id": "13",
            "sentence": "यह उपाय शल्य-चिकित्सक को बिना किसी हस्तक्षेप के ट्यूमर को हटाने में मदद करता है।",
            "sentence_id": "oct-31-2022-part1Patient_Information_Sheet-Riya_Lal_Study_hin_target_014"
        },
        {
            "project_id": "13",
            "sentence": "कभी-कभी, उपायों के बावजूद, मस्तिष्क की आवरण परत शल्य-चिकित्सीय क्षेत्र में उभर सकती है ।",
            "sentence_id": "oct-31-2022-part1Patient_Information_Sheet-Riya_Lal_Study_hin_target_015a"
        },
        {
            "project_id": "13",
            "sentence": "और उपकरण में फंस सकती है ।",
            "sentence_id": "oct-31-2022-part1Patient_Information_Sheet-Riya_Lal_Study_hin_target_015b"
        },
        {
            "project_id": "13",
            "sentence": "तथा कवर परतों में एक छेद बना सकती है, जिसके माध्यम से सीएसएफ नामक मस्तिष्क तरल पदार्थ का बाहर रिसाव हो सकता है।",
            "sentence_id": "oct-31-2022-part1Patient_Information_Sheet-Riya_Lal_Study_hin_target_015c"
        },
        {
            "project_id": "13",
            "sentence": "इस रिसाव को रोकने के लिए, एनेस्थेसियोलॉजिस्ट पीठ में एक नली डालता है ।",
            "sentence_id": "oct-31-2022-part1Patient_Information_Sheet-Riya_Lal_Study_hin_target_016a"
        },
        {
            "project_id": "13",
            "sentence": "और अनुभवजन्य रूप से सीएसएफ को हटा देता है",
            "sentence_id": "oct-31-2022-part1Patient_Information_Sheet-Riya_Lal_Study_hin_target_016b"
        },
        {
            "project_id": "13",
            "sentence": "जिससे नाक के माध्यम से उभार कम हो जाता है।",
            "sentence_id": "oct-31-2022-part1Patient_Information_Sheet-Riya_Lal_Study_hin_target_016c"
        },
        {
            "project_id": "13",
            "sentence": "इन सभी उपायों के बावजूद, शल्य-चिकित्स के दौरान या शल्य-चिकित्स के बाद कुछ मामलों में रिसाव की संभावना है।",
            "sentence_id": "oct-31-2022-part1Patient_Information_Sheet-Riya_Lal_Study_hin_target_017"
        },
        {
            "project_id": "13",
            "sentence": "सीएसएफ रिसाव के कारण संक्रमण की संभावना बढ जाती है।",
            "sentence_id": "oct-31-2022-part1Patient_Information_Sheet-Riya_Lal_Study_hin_target_018"
        },
        {
            "project_id": "13",
            "sentence": "इसके अलावा, आपको 3 से 5 दिनों के लिए बिस्तर पर आराम करने की आवश्यकता है।",
            "sentence_id": "oct-31-2022-part1Patient_Information_Sheet-Riya_Lal_Study_hin_target_019a"
        },
        {
            "project_id": "13",
            "sentence": "जिससे आपके अस्पताल में रहने की अवधि बढा सकती है।",
            "sentence_id": "oct-31-2022-part1Patient_Information_Sheet-Riya_Lal_Study_hin_target_019b"
        },
        {
            "project_id": "13",
            "sentence": "मैनिटॉल एक दवा है।",
            "sentence_id": "oct-31-2022-part1Patient_Information_Sheet-Riya_Lal_Study_hin_target_020a"
        },
        {
            "project_id": "13",
            "sentence": "अध्ययन डिजाइन।",
            "sentence_id": "oct-31-2022-part1Patient_Information_Sheet-Riya_Lal_Study_hin_target_022H"
        },
        {
            "project_id": "13",
            "sentence": "आपकी शल्य-चिकित्सा के दौरान मानक एनेस्थीसिया दवाओं और निगरानी तकनीकों का उपयोग किया जाएगा।",
            "sentence_id": "oct-31-2022-part1Patient_Information_Sheet-Riya_Lal_Study_hin_target_023"
        },
        {
            "project_id": "13",
            "sentence": "यदि आप भाग लेने के लिए तैयार हैं ।",
            "sentence_id": "oct-31-2022-part1Patient_Information_Sheet-Riya_Lal_Study_hin_target_024a"
        },
        {
            "project_id": "13",
            "sentence": "तो आपको दो समूहों में से एक में यादृच्छिक रूप से भेजा जाएगा।",
            "sentence_id": "oct-31-2022-part1Patient_Information_Sheet-Riya_Lal_Study_hin_target_024b"
        },
        {
            "project_id": "13",
            "sentence": "एक समूह को मैनिटॉल नामक दवा प्राप्त होगी ।",
            "sentence_id": "oct-31-2022-part1Patient_Information_Sheet-Riya_Lal_Study_hin_target_025a"
        },
        {
            "project_id": "13",
            "sentence": "और दूसरे समूह को सामान्य अंतःशिरा सेलाइन तरल पदार्थ की मात्रा प्राप्त होगी।",
            "sentence_id": "oct-31-2022-part1Patient_Information_Sheet-Riya_Lal_Study_hin_target_025b"
        },
        {
            "project_id": "13",
            "sentence": "आपके निर्धारित समूह के अनुसार, आपको दवाएं दी जाएंगी।",
            "sentence_id": "oct-31-2022-part1Patient_Information_Sheet-Riya_Lal_Study_hin_target_026"
        },
        {
            "project_id": "13",
            "sentence": "इसके अलावा अगर सीएसएफ रिसाव होता है ।",
            "sentence_id": "oct-31-2022-part1Patient_Information_Sheet-Riya_Lal_Study_hin_target_028a"
        },
        {
            "project_id": "13",
            "sentence": "तो हम आपकी पीठ पर सीएसएफ तरल पदार्थ को नियंत्रित तरीके से हटाने के लिए एक ट्यूब डालेंगे, जो नाक के माध्यम से होने वाले रिसाव को रोकेगी।",
            "sentence_id": "oct-31-2022-part1Patient_Information_Sheet-Riya_Lal_Study_hin_target_028b"
        },
        {
            "project_id": "13",
            "sentence": "लाभ।",
            "sentence_id": "oct-31-2022-part1Patient_Information_Sheet-Riya_Lal_Study_hin_target_029H"
        },
        {
            "project_id": "13",
            "sentence": "इस शोध में, हम यह अध्ययन करने की योजना बना रहे हैं।",
            "sentence_id": "oct-31-2022-part1Patient_Information_Sheet-Riya_Lal_Study_hin_target_021a"
        },
        {
            "project_id": "13",
            "sentence": "कि क्या मैनिटॉल का प्रयोग शल्य-चिकित्सीय स्थान पर उभार को कम करने में मदद करता है।",
            "sentence_id": "oct-31-2022-part1Patient_Information_Sheet-Riya_Lal_Study_hin_target_021b"
        },
        {
            "project_id": "13",
            "sentence": "जिससे मस्तिष्क की आवरण परत में चोट लगने की संभावना कम हो जाती है",
            "sentence_id": "oct-31-2022-part1Patient_Information_Sheet-Riya_Lal_Study_hin_target_021c"
        },
        {
            "project_id": "13",
            "sentence": "और सीएसएफ रिसाव कम हो जाता है।",
            "sentence_id": "oct-31-2022-part1Patient_Information_Sheet-Riya_Lal_Study_hin_target_021d"
        },
        {
            "project_id": "13",
            "sentence": "जो मस्तिष्क को राहत प्रदान करता है।",
            "sentence_id": "oct-31-2022-part1Patient_Information_Sheet-Riya_Lal_Study_hin_target_020c"
        },
        {
            "project_id": "13",
            "sentence": "और हमें सूचित करेगा।",
            "sentence_id": "oct-31-2022-part1Patient_Information_Sheet-Riya_Lal_Study_hin_target_027b"
        },
        {
            "project_id": "13",
            "sentence": "ऑपरेशन के दौरान, शल्य-चिकित्सक मस्तिष्क उभार की डिग्री का आकलन करेगा ।",
            "sentence_id": "oct-31-2022-part1Patient_Information_Sheet-Riya_Lal_Study_hin_target_027a"
        },
        {
            "project_id": "13",
            "sentence": "मैनिटॉल का प्रयोग मस्तिष्क उभार, जिससे द्रव रिसाव होता है, को कम करने में मदद कर सकता है ।",
            "sentence_id": "oct-31-2022-part1Patient_Information_Sheet-Riya_Lal_Study_hin_target_030a"
        },
        {
            "project_id": "13",
            "sentence": "या नहीं भी कर सकता है।",
            "sentence_id": "oct-31-2022-part1Patient_Information_Sheet-Riya_Lal_Study_hin_target_030b"
        },
        {
            "project_id": "13",
            "sentence": "यदि इस अध्ययन के परिणाम यह साबित करते हैं।",
            "sentence_id": "oct-31-2022-part1Patient_Information_Sheet-Riya_Lal_Study_hin_target_031a"
        },
        {
            "project_id": "13",
            "sentence": "कि मैनिटॉल के प्रयोग से उभार और द्रव रिसाव को कम करने में मदद मिलती है ।",
            "sentence_id": "oct-31-2022-part1Patient_Information_Sheet-Riya_Lal_Study_hin_target_031b"
        },
        {
            "project_id": "13",
            "sentence": "तो हम इस उपाय को भविष्य में इसी तरह की शल्य-चिकित्सा से गुजरने वाले रोगियों की नियमित देखभाल के हिस्से के रूप में जारी रखेंगे।",
            "sentence_id": "oct-31-2022-part1Patient_Information_Sheet-Riya_Lal_Study_hin_target_031c"
        },
        {
            "project_id": "13",
            "sentence": "यह परीक्षण एक नियंत्रित परीक्षण है, जिसमें मैनिटॉल प्राप्त करने की केवल 50% संभावना है ।",
            "sentence_id": "oct-31-2022-part1Patient_Information_Sheet-Riya_Lal_Study_hin_target_032a"
        },
        {
            "project_id": "13",
            "sentence": "इसलिए आपको प्रत्यक्ष लाभ नहीं भी मिल सकता है।",
            "sentence_id": "oct-31-2022-part1Patient_Information_Sheet-Riya_Lal_Study_hin_target_032b"
        },
        {
            "project_id": "13",
            "sentence": "जोखिम।",
            "sentence_id": "oct-31-2022-part1Patient_Information_Sheet-Riya_Lal_Study_hin_target_033H"
        },
        {
            "project_id": "13",
            "sentence": "कई दशकों से न्यूरोसर्जरी में मस्तिष्क को राहत पहुंचाने के लिए मैनिटॉल का उपयोग नियमित रूप से किया जाता रहा है।",
            "sentence_id": "oct-31-2022-part1Patient_Information_Sheet-Riya_Lal_Study_hin_target_034"
        },
        {
            "project_id": "13",
            "sentence": "इसका उपयोग मूत्र उत्पादन बढा सकता है ।",
            "sentence_id": "oct-31-2022-part1Patient_Information_Sheet-Riya_Lal_Study_hin_target_035a"
        },
        {
            "project_id": "13",
            "sentence": "और रक्त में नमक के स्तर को बदल सकता है।",
            "sentence_id": "oct-31-2022-part1Patient_Information_Sheet-Riya_Lal_Study_hin_target_035b"
        },
        {
            "project_id": "13",
            "sentence": "हम नमक के स्तर की निगरानी के लिए रक्त परीक्षण करेंगे ।",
            "sentence_id": "oct-31-2022-part1Patient_Information_Sheet-Riya_Lal_Study_hin_target_036a"
        },
        {
            "project_id": "13",
            "sentence": "और उसका उचित इलाज करेंगे।",
            "sentence_id": "oct-31-2022-part1Patient_Information_Sheet-Riya_Lal_Study_hin_target_036b"
        },
        {
            "project_id": "13",
            "sentence": "मूत्र उत्पादन के आधार पर द्रव दिया जाएगा।",
            "sentence_id": "oct-31-2022-part1Patient_Information_Sheet-Riya_Lal_Study_hin_target_037"
        },
        {
            "project_id": "13",
            "sentence": "इसलिए यदि आप अध्ययन में भाग ले रहे हैं ।",
            "sentence_id": "oct-31-2022-part1Patient_Information_Sheet-Riya_Lal_Study_hin_target_038a"
        },
        {
            "project_id": "13",
            "sentence": "तो इसमें कोई बडा जोखिम नहीं है।",
            "sentence_id": "oct-31-2022-part1Patient_Information_Sheet-Riya_Lal_Study_hin_target_038b"
        },
        {
            "project_id": "13",
            "sentence": "अध्ययन जांचकर्ताओं द्वारा नियमित अंतराल पर आपकी निगरानी की जाएगी ।",
            "sentence_id": "oct-31-2022-part1Patient_Information_Sheet-Riya_Lal_Study_hin_target_039a"
        },
        {
            "project_id": "13",
            "sentence": "इसलिए भागीदारी से जोखिम के बजाय लाभ हैं।",
            "sentence_id": "oct-31-2022-part1Patient_Information_Sheet-Riya_Lal_Study_hin_target_039b"
        },
        {
            "project_id": "13",
            "sentence": "स्वैच्छिक भागीदारी।",
            "sentence_id": "oct-31-2022-part1Patient_Information_Sheet-Riya_Lal_Study_hin_target_040H"
        },
        {
            "project_id": "13",
            "sentence": "इस अध्ययन में आपकी भागीदारी स्वैच्छिक है।",
            "sentence_id": "oct-31-2022-part1Patient_Information_Sheet-Riya_Lal_Study_hin_target_041"
        },
        {
            "project_id": "13",
            "sentence": "आप इस अध्ययन में नहीं होने का फैसला कर सकते हैं ।",
            "sentence_id": "oct-31-2022-part1Patient_Information_Sheet-Riya_Lal_Study_hin_target_042a"
        },
        {
            "project_id": "13",
            "sentence": "या आप पहले तो अध्ययन में भाग ले सकते हैं ।",
            "sentence_id": "oct-31-2022-part1Patient_Information_Sheet-Riya_Lal_Study_hin_target_042b"
        },
        {
            "project_id": "13",
            "sentence": "और फिर बाद में अपना मन बदल सकते हैं।",
            "sentence_id": "oct-31-2022-part1Patient_Information_Sheet-Riya_Lal_Study_hin_target_042c"
        },
        {
            "project_id": "13",
            "sentence": "अपनी देखभाल को प्रभावित किए बिना, आप किसी भी समय अध्ययन छोड सकते हैं।",
            "sentence_id": "oct-31-2022-part1Patient_Information_Sheet-Riya_Lal_Study_hin_target_043"
        },
        {
            "project_id": "13",
            "sentence": "इस अध्ययन में भाग लेने के लिए आपको अतिरिक्त धन का भुगतान नहीं करना होगा।",
            "sentence_id": "oct-31-2022-part1Patient_Information_Sheet-Riya_Lal_Study_hin_target_044"
        },
        {
            "project_id": "13",
            "sentence": "इसके अलावा, आपको इस अध्ययन में भाग लेने के लिए कोई प्रतिपूर्ति नहीं मिलेगी।",
            "sentence_id": "oct-31-2022-part1Patient_Information_Sheet-Riya_Lal_Study_hin_target_045"
        },
        {
            "project_id": "13",
            "sentence": "रोगी सूचना-पत्रक ।",
            "sentence_id": "oct-31-2022-part1Patient_Information_Sheet-Riya_Lal_Study_hin_target_001INFOSHEET"
        },
        {
            "project_id": "13",
            "sentence": "पिट्यूटरी एडिनोमा को निकालने के लिये, आर्चनॉइड उभार में मैनिटॉल देने का प्रभाव और एंडोस्कोपिक ट्रांसनेसल, ट्रांसस्पेनोइडल (टीएनटीएस) से गुजरने वाले रोगियों में मस्तिष्क द्रव (सीएसएफ) के रिसाव की घटना - एक यादृच्छिक नियंत्रित परीक्षण।",
            "sentence_id": "oct-31-2022-part1Patient_Information_Sheet-Riya_Lal_Study_hin_target_002TITLE"
        },
        {
            "project_id": "13",
            "sentence": "जिसकी सभी प्रकार की मस्तिष्क संबंधी शल्य-चिकित्सा के लिए नियमित रूप से प्रयोग किया जाता है,जिसके लिए खोपडी की हड्डी को खोलने की आवश्यकता होती है।",
            "sentence_id": "oct-31-2022-part1Patient_Information_Sheet-Riya_Lal_Study_hin_target_020b"
        }
    ]
}